whose_encoder/__init__.py
whose_encoder/decoder.py
whose_encoder/encoder.py
whose_encoder/fun.py
whose_encoder-0.5.0.dist-info/licenses/LICENSE
whose_encoder-0.5.0.dist-info/METADATA
whose_encoder-0.5.0.dist-info/WHEEL
whose_encoder-0.5.0.dist-info/entry_points.txt
whose_encoder-0.5.0.dist-info/top_level.txt
whose_encoder-0.5.0.dist-info/RECORD
